testpackagesanc/__init__.py
testpackagesanc/config.py
testpackagesanc-1.1.8.data/scripts/config.py
testpackagesanc-1.1.8.dist-info/LICENSE
testpackagesanc-1.1.8.dist-info/METADATA
testpackagesanc-1.1.8.dist-info/WHEEL
testpackagesanc-1.1.8.dist-info/entry_points.txt
testpackagesanc-1.1.8.dist-info/top_level.txt
testpackagesanc-1.1.8.dist-info/RECORD
