Metadata-Version: 2.1
Name: testpackagesanc
Version: 1.1.8
Summary: testConfig
Home-page: UNKNOWN
Author: Jin Xin
Author-email: jin.xin@accenture.com
License: MIT
Platform: UNKNOWN
Classifier: Programming Language :: Python :: 3.7
Classifier: License :: OSI Approved :: MIT License
Classifier: Operating System :: OS Independent
